{
  "sport": "basketball",
  "league": "wnba",
  "date": "20260716",
  "count": 2,
  "games": [
    {
      "id": "401857071",
      "name": "Portland Fire at Washington Mystics",
      "shortName": "POR @ WSH",
      "date": "2026-07-16T23:00Z",
      "state": "pre",
      "status": "7/16 - 7:00 PM EDT",
      "completed": false,
      "home": {
        "id": "16",
        "abbr": "WSH",
        "name": "Washington Mystics",
        "score": "0"
      },
      "away": {
        "id": "132052",
        "abbr": "POR",
        "name": "Portland Fire",
        "score": "0"
      }
    },
    {
      "id": "401857072",
      "name": "New York Liberty at Dallas Wings",
      "shortName": "NY @ DAL",
      "date": "2026-07-17T01:00Z",
      "state": "pre",
      "status": "7/16 - 9:00 PM EDT",
      "completed": false,
      "home": {
        "id": "3",
        "abbr": "DAL",
        "name": "Dallas Wings",
        "score": "0"
      },
      "away": {
        "id": "9",
        "abbr": "NY",
        "name": "New York Liberty",
        "score": "0"
      }
    }
  ]
}
